{"triples": [{"subject": "China", "relation": "LEADING_ELECTRIC_VEHICLE_SALES", "object": "9.49 million units", "doc_id": "doc_57", "evidence": "leading at 9.49 million units"}, {"subject": "KPMG", "relation": "HIGHLIGHTS", "object": "diversification strategies", "doc_id": "doc_57", "evidence": "highlights diversification strategies"}, {"subject": "US EV market", "relation": "PRESENTS_CASE_FOR", "object": "sustainable investments", "doc_id": "doc_57", "evidence": "presents compelling case for sustainable investments"}, {"subject": "Japan", "relation": "CPI_INDICATES", "object": "ongoing inflation challenges (core CPI rose 2.0% year-over-year in September)", "doc_id": "doc_57", "evidence": "indicate ongoing inflation challenges"}, {"subject": "China", "relation": "GDP_GROWTH_PROJECTION", "object": "below 4% for the year", "doc_id": "doc_57", "evidence": "projects GDP growth to dip below 4%"}, {"subject": "US", "relation": "INFLATION_MODERATION", "object": "3.1% as of mid-2024", "doc_id": "doc_57", "evidence": "US inflation has moderated to around 3.1%"}], "entities": [{"entity": "KPMG", "etype": "organization", "subtype": "company"}, {"entity": "US EV market", "etype": "organization", "subtype": "market"}]}